{
    "Indexes": {
        "operator-metadata": {
            "2.15": {
                "OSBSImage": "registry-proxy.engineering.redhat.com/rh-osbs/codeready-workspaces-operator-metadata:2.15-21",
                "quayImage": "quay.io/crw/crw-2-rhel8-operator-metadata:2.15-21",
                "tag": "2.15-21"
            }
        },
        "operator-bundle": {
            "2.15": {
                "v4.8": {
                    "iibURL": "registry-proxy.engineering.redhat.com/rh-osbs/iib:162785",
                    "iibTag": "162785"
                },
                "v4.9": {
                    "iibURL": "registry-proxy.engineering.redhat.com/rh-osbs/iib:162790",
                    "iibTag": "162790"
                },
                "v4.10": {
                    "iibURL": "registry-proxy.engineering.redhat.com/rh-osbs/iib:162794",
                    "iibTag": "162794"
                },
                "OSBSImage": "registry-proxy.engineering.redhat.com/rh-osbs/codeready-workspaces-operator-bundle:2.15-221",
                "quayImage": "quay.io/crw/crw-2-rhel8-operator-bundle:2.15-221",
                "tag": "2.15-221"
            }
        }
    }
}
