{
    "Indexes": {
        "operator-bundle": {
            "3.9": {
                "v4.10": {
                    "iibURL": "registry-proxy.engineering.redhat.com/rh-osbs/iib:542445",
                    "iibTag": "542445"
                },
                "OSBSImage": "registry-proxy.engineering.redhat.com/rh-osbs/devspaces-devspaces-operator-bundle:3.9-5",
                "quayImage": "quay.io/devspaces/devspaces-operator-bundle:3.9-5",
                "tag": "3.9-5"
            }
        }
    }
}
