{
    "Indexes": {
        "operator-bundle": {
            "3.6": {
                "v4.10": {
                    "iibURL": "registry-proxy.engineering.redhat.com/rh-osbs/iib:437106",
                    "iibTag": "437106"
                },
                "v4.11": {
                    "iibURL": "registry-proxy.engineering.redhat.com/rh-osbs/iib:437107",
                    "iibTag": "437107"
                },
                "OSBSImage": "registry-proxy.engineering.redhat.com/rh-osbs/devspaces-devspaces-operator-bundle:3.6-39",
                "quayImage": "quay.io/devspaces/devspaces-operator-bundle:3.6-39",
                "tag": "3.6-39"
            }
        }
    }
}
