{
    "Indexes": {
        "operator-bundle": {
            "3.12": {
                "v4.12": {
                    "iibURL": "registry-proxy.engineering.redhat.com/rh-osbs/iib:677141",
                    "iibTag": "677141"
                },
                "OSBSImage": "registry-proxy.engineering.redhat.com/rh-osbs/devspaces-devspaces-operator-bundle:3.12-165",
                "quayImage": "quay.io/devspaces/devspaces-operator-bundle:3.12-165",
                "tag": "3.12-165"
            }
        }
    }
}
